a2y_fef.cp38-win_amd64.pyd
a2y_fef-0.9.12.dist-info/LICENSE
a2y_fef-0.9.12.dist-info/METADATA
a2y_fef-0.9.12.dist-info/WHEEL
a2y_fef-0.9.12.dist-info/top_level.txt
a2y_fef-0.9.12.dist-info/RECORD
