Metadata-Version: 2.1
Name: a2y-fef
Version: 0.9.12
Summary: 此模块实现了一个总线设备管理器。所有被管理的设备使用 Mewtocol 协议通信，作为从机。通常总线类型是 RS485。对内核科技RS485接口的输入输出模块、单轴运动控制模块提供高层次API支持。
Home-page: http://www.sorobust.com/a2y/fef.html
Author: Yu Han
Author-email: hanjunyu@163.com
License: Private
Platform: Windows
Platform: Linux
Classifier: Development Status :: 4 - Beta
Classifier: Intended Audience :: Developers
Classifier: License :: Free For Educational Use
Classifier: Programming Language :: Python :: 3.5
Classifier: Operating System :: Microsoft :: Windows :: Windows 10
Classifier: Operating System :: POSIX :: Linux
License-File: LICENSE
Requires-Dist: a2y-mew >=0.9.3
